{
    "Table Schema": "noobschema",
    "Tables": [
      {
        "Table Name": "lineitem",
        "Table Columns": [
          {
            "Column Name": "l_orderkey",
            "Data Type": "int",
            "Data Distribution": [0,100]
          },
          {
            "Column Name": "l_partkey",
            "Data Type": "int",
            "Data Distribution": [0,100]
          },
          {
            "Column Name": "l_suppkey",
            "Data Type": "int",
            "Data Distribution": [0,100]
          },
          {
            "Column Name": "linenumber",
            "Data Type": "int",
            "Data Distribution": [0,100]
          },
          {
            "Column Name": "l_quantity",
            "Data Type": "int",
            "Data Distribution": [0,100]
          },
          {
            "Column Name": "l_extendedprice",
            "Data Type": "int",
            "Data Distribution": [0,100]
          },
          {
            "Column Name": "l_discount",
            "Data Type": "int",
            "Data Distribution": [0,100]
          },
          {
            "Column Name": "l_tax",
            "Data Type": "int",
            "Data Distribution": [0,100]
          },
          {
            "Column Name": "l_returnflag",
            "Data Type": "int",
            "Data Distribution": [0,100]
          },
          {
            "Column Name": "l_linestatus",
            "Data Type": "int",
            "Data Distribution": [0,100]
          },
          {
            "Column Name": "l_shipdate",
            "Data Type": "int",
            "Data Distribution": [0,100]
          },
          {
            "Column Name": "l_commitdate",
            "Data Type": "int",
            "Data Distribution": [0,100]
          },
          {
            "Column Name": "l_receiptdate",
            "Data Type": "int",
            "Data Distribution": [0,100]
          },
          {
            "Column Name": "l_shipinstruct",
            "Data Type": "int",
            "Data Distribution": [0,100]
          },
          {
            "Column Name": "l_shipmode",
            "Data Type": "int",
            "Data Distribution": [0,100]
          },
          {
            "Column Name": "l_comment",
            "Data Type": "int",
            "Data Distribution": [0,100]
          }
        ],
        "Column Distribution" : [],
        "Primary Key": {
          "Name": "",
          "Data Type": ""
        },
        "Foreign Key": [
          {
            "Foreign Key Name": "",
            "Foreign Key Type": "",
            "Referenced Table": "",
            "Referenced Primary Key": "",
            "Referenced Primary Key Type": ""
          }
        ]
      },
      {
        "Table Name": "part",
        "Table Columns": [
          {
            "Column Name": "p_partkey",
            "Data Type": "int",
            "Data Distribution": [0,100]
          },
          {
            "Column Name": "p_name",
            "Data Type": "int",
            "Data Distribution": [0,100]
          },
          {
            "Column Name": "p_mfgr",
            "Data Type": "int",
            "Data Distribution": [0,100]
          },
          {
            "Column Name": "p_brand",
            "Data Type": "int",
            "Data Distribution": [0,100]
          },
          {
            "Column Name": "p_type",
            "Data Type": "int",
            "Data Distribution": [0,100]
          },
          {
            "Column Name": "p_size",
            "Data Type": "int",
            "Data Distribution": [0,100]
          },
          {
            "Column Name": "p_container",
            "Data Type": "int",
            "Data Distribution": [0,100]
          },
          {
            "Column Name": "p_retailprice",
            "Data Type": "int",
            "Data Distribution": [0,100]
          },
          {
            "Column Name": "p_comment",
            "Data Type": "int",
            "Data Distribution": [0,100]
          }
        ],
        "Column Distribution" : [],
        "Primary Key": {
          "Name": "",
          "Data Type": ""
        },
        "Foreign Key": [
          {
            "Foreign Key Name": "",
            "Foreign Key Type": "",
            "Referenced Table": "",
            "Referenced Primary Key": "",
            "Referenced Primary Key Type": ""
          }
        ]
      },
      {
        "Table Name": "orders",
        "Table Columns": [
          {
            "Column Name": "o_orderkey",
            "Data Type": "varchar",
            "Data Distribution": ["minv","maxv"]
          },
          {
            "Column Name": "o_custkey",
            "Data Type": "int",
            "Data Distribution": [0,100]
          },
          {
            "Column Name": "o_orderstatus",
            "Data Type": "int",
            "Data Distribution": [0,100]
          },
          {
            "Column Name": "o_totalprice",
            "Data Type": "int",
            "Data Distribution": [0,100]
          },
          {
            "Column Name": "o_orderdate",
            "Data Type": "int",
            "Data Distribution": [0,100]
          },
          {
            "Column Name": "o_orderpriority",
            "Data Type": "int",
            "Data Distribution": [0,100]
          },
          {
            "Column Name": "o_clerk",
            "Data Type": "int",
            "Data Distribution": [0,100]
          },
          {
            "Column Name": "o_shippriority",
            "Data Type": "int",
            "Data Distribution": [0,100]
          },
          {
            "Column Name": "o_comment",
            "Data Type": "int",
            "Data Distribution": [0,100]
          }
        ],
        "Column Distribution" : [],
        "Primary Key": {
          "Name": "",
          "Data Type": ""
        },
        "Foreign Key": [
          {
            "Foreign Key Name": "",
            "Foreign Key Type": "",
            "Referenced Table": "",
            "Referenced Primary Key": "",
            "Referenced Primary Key Type": ""
          }
        ]
      },
      {
        "Table Name": "partsupp",
        "Table Columns": [
          {
            "Column Name": "ps_partkey",
            "Data Type": "int",
            "Data Distribution": [0,100]
          },
          {
            "Column Name": "ps_suppkey",
            "Data Type": "varchar",
            "Data Distribution": ["minv","maxv"]
          },
          {
            "Column Name": "ps_availqty",
            "Data Type": "int",
            "Data Distribution": [0,100]
          },
          {
            "Column Name": "ps_supplycost",
            "Data Type": "int",
            "Data Distribution": [0,100]
          },
          {
            "Column Name": "ps_comment",
            "Data Type": "int",
            "Data Distribution": [0,100]
          }
        ],
        "Column Distribution" : [],
        "Primary Key": {
          "Name": "",
          "Data Type": ""
        },
        "Foreign Key": [
          {
            "Foreign Key Name": "",
            "Foreign Key Type": "",
            "Referenced Table": "",
            "Referenced Primary Key": "",
            "Referenced Primary Key Type": ""
          }
        ]
      },
      {
        "Table Name": "supplier",
        "Table Columns": [
          {
            "Column Name": "s_suppkey",
            "Data Type": "varchar",
            "Data Distribution": ["minv","maxv"]
          },
          {
            "Column Name": "s_name",
            "Data Type": "int",
            "Data Distribution": [0,100]
          },
          {
            "Column Name": "s_address",
            "Data Type": "int",
            "Data Distribution": [0,100]
          },
          {
            "Column Name": "s_nationkey",
            "Data Type": "int",
            "Data Distribution": [0,100]
          },
          {
            "Column Name": "s_phone",
            "Data Type": "int",
            "Data Distribution": [0,100]
          },
          {
            "Column Name": "s_acctbal",
            "Data Type": "int",
            "Data Distribution": [0,100]
          },
          {
            "Column Name": "s_comment",
            "Data Type": "int",
            "Data Distribution": [0,100]
          }
        ],
        "Column Distribution" : [],
        "Primary Key": {
          "Name": "",
          "Data Type": ""
        },
        "Foreign Key": [
          {
            "Foreign Key Name": "",
            "Foreign Key Type": "",
            "Referenced Table": "",
            "Referenced Primary Key": "",
            "Referenced Primary Key Type": ""
          }
        ]
      },
      {
        "Table Name": "nation",
        "Table Columns": [
          {
            "Column Name": "n_nationkey",
            "Data Type": "int",
            "Data Distribution": [0,100]
          },
          {
            "Column Name": "n_name",
            "Data Type": "varchar",
            "Data Distribution": ["minv","maxv"]
          },
          {
            "Column Name": "n_regionkey",
            "Data Type": "int",
            "Data Distribution": [0,100]
          },
          {
            "Column Name": "n_comment",
            "Data Type": "int",
            "Data Distribution": [0,100]
          }
        ],
        "Column Distribution" : [],
        "Primary Key": {
          "Name": "",
          "Data Type": ""
        },
        "Foreign Key": [
          {
            "Foreign Key Name": "",
            "Foreign Key Type": "",
            "Referenced Table": "",
            "Referenced Primary Key": "",
            "Referenced Primary Key Type": ""
          }
        ]
      },
      {
        "Table Name": "customer",
        "Table Columns": [
          {
            "Column Name": "c_custkey",
            "Data Type": "int",
            "Data Distribution": [0,100]
          },
          {
            "Column Name": "c_name",
            "Data Type": "varchar",
            "Data Distribution": ["minv","maxv"]
          },
          {
            "Column Name": "c_address",
            "Data Type": "int",
            "Data Distribution": [0,100]
          },
          {
            "Column Name": "c_nationkey",
            "Data Type": "int",
            "Data Distribution": [0,100]
          },
          {
            "Column Name": "c_phone",
            "Data Type": "int",
            "Data Distribution": [0,100]
          },
          {
            "Column Name": "c_acctbal",
            "Data Type": "int",
            "Data Distribution": [0,100]
          },
          {
            "Column Name": "c_mktsegment",
            "Data Type": "int",
            "Data Distribution": [0,100]
          },
          {
            "Column Name": "c_comment",
            "Data Type": "int",
            "Data Distribution": [0,100]
          }
        ],
        "Column Distribution" : [],
        "Primary Key": {
          "Name": "",
          "Data Type": ""
        },
        "Foreign Key": [
          {
            "Foreign Key Name": "",
            "Foreign Key Type": "",
            "Referenced Table": "",
            "Referenced Primary Key": "",
            "Referenced Primary Key Type": ""
          }
        ]
      },
      {
        "Table Name": "region",
        "Table Columns": [
          {
            "Column Name": "r_regionkey",
            "Data Type": "int",
            "Data Distribution": [0,100]
          },
          {
            "Column Name": "r_name",
            "Data Type": "varchar",
            "Data Distribution": ["minv","maxv"]
          },
          {
            "Column Name": "r_comment",
            "Data Type": "int",
            "Data Distribution": [0,100]
          }
        ],
        "Column Distribution" : [],
        "Primary Key": {
          "Name": "",
          "Data Type": ""
        },
        "Foreign Key": [
          {
            "Foreign Key Name": "",
            "Foreign Key Type": "",
            "Referenced Table": "",
            "Referenced Primary Key": "",
            "Referenced Primary Key Type": ""
          }
        ]
      },
      {
        "Table Name": "revenue0",
        "Table Columns": [
          {
            "Column Name": "total_revenue",
            "Data Type": "int",
            "Data Distribution": [0,100]
          }
        ],
        "Column Distribution" : [],
        "Primary Key": {
          "Name": "",
          "Data Type": ""
        },
        "Foreign Key": [
          {
            "Foreign Key Name": "",
            "Foreign Key Type": "",
            "Referenced Table": "",
            "Referenced Primary Key": "",
            "Referenced Primary Key Type": ""
          }
        ]
      }
    ]
  }
  